NOTICE
splunk_add_on_ucc_framework/__init__.py
splunk_add_on_ucc_framework/__main__.py
splunk_add_on_ucc_framework/app_manifest.py
splunk_add_on_ucc_framework/auto_gen_comparator.py
splunk_add_on_ucc_framework/commands/__init__.py
splunk_add_on_ucc_framework/commands/build.py
splunk_add_on_ucc_framework/commands/import_from_aob.py
splunk_add_on_ucc_framework/commands/import_from_aob.sh
splunk_add_on_ucc_framework/commands/imports.py
splunk_add_on_ucc_framework/commands/init.py
splunk_add_on_ucc_framework/commands/modular_alert_builder/__init__.py
splunk_add_on_ucc_framework/commands/modular_alert_builder/alert_actions_py_gen.py
splunk_add_on_ucc_framework/commands/modular_alert_builder/arf_consts.py
splunk_add_on_ucc_framework/commands/modular_alert_builder/arf_template/alert_action.py.template
splunk_add_on_ucc_framework/commands/modular_alert_builder/arf_template/alert_action_helper.py.template
splunk_add_on_ucc_framework/commands/modular_alert_builder/builder.py
splunk_add_on_ucc_framework/commands/modular_alert_builder/normalize.py
splunk_add_on_ucc_framework/commands/openapi_generator/__init__.py
splunk_add_on_ucc_framework/commands/openapi_generator/json_to_object.py
splunk_add_on_ucc_framework/commands/openapi_generator/oas.py
splunk_add_on_ucc_framework/commands/openapi_generator/object_to_json.py
splunk_add_on_ucc_framework/commands/openapi_generator/ucc_to_oas.py
splunk_add_on_ucc_framework/commands/package.py
splunk_add_on_ucc_framework/commands/publish.py
splunk_add_on_ucc_framework/commands/rest_builder/__init__.py
splunk_add_on_ucc_framework/commands/rest_builder/builder.py
splunk_add_on_ucc_framework/commands/rest_builder/endpoint/__init__.py
splunk_add_on_ucc_framework/commands/rest_builder/endpoint/base.py
splunk_add_on_ucc_framework/commands/rest_builder/endpoint/datainput.py
splunk_add_on_ucc_framework/commands/rest_builder/endpoint/field.py
splunk_add_on_ucc_framework/commands/rest_builder/endpoint/multiple_model.py
splunk_add_on_ucc_framework-6.1.0.dist-info/METADATA
splunk_add_on_ucc_framework-6.1.0.dist-info/WHEEL
splunk_add_on_ucc_framework-6.1.0.dist-info/entry_points.txt
splunk_add_on_ucc_framework-6.1.0.dist-info/licenses/LICENSE
splunk_add_on_ucc_framework-6.1.0.dist-info/licenses/NOTICE
splunk_add_on_ucc_framework-6.1.0.dist-info/RECORD
