Metadata-Version: 2.4
Name: splunk_add_on_ucc_framework
Version: 6.1.0
Summary: Splunk Add-on SDK formerly UCC is a build and code generation framework
License: Apache-2.0
License-File: LICENSE
License-File: NOTICE
Keywords: splunk,ucc
Author: Splunk
Author-email: addonfactory@splunk.com
Requires-Python: >=3.9,<3.14
Classifier: Development Status :: 5 - Production/Stable
Classifier: Intended Audience :: Developers
Classifier: License :: OSI Approved :: Apache Software License
Classifier: Programming Language :: Python
Classifier: Programming Language :: Python :: 3
Classifier: Programming Language :: Python :: 3.9
Classifier: Programming Language :: Python :: 3.10
Classifier: Programming Language :: Python :: 3.11
Classifier: Programming Language :: Python :: 3.12
Classifier: Programming Language :: Python :: 3.13
Classifier: Programming Language :: Python :: 3.14
Classifier: Topic :: Software Development :: Code Generators
Classifier: Topic :: Software Development :: Libraries :: Python Modules
Provides-Extra: validate
Requires-Dist: PyYAML (>=6.0,<7.0)
Requires-Dist: addonfactory-splunk-conf-parser-lib (>=1.0.0,<2.0.0)
Requires-Dist: certifi (>=2025.6.15,<2026.0.0)
Requires-Dist: colorama (>=0.4.6,<0.5.0)
Requires-Dist: defusedxml (>=0.7.1,<0.8.0)
Requires-Dist: dunamai (>=1.22.0,<2.0.0)
Requires-Dist: jinja2 (>=3.1.6,<4)
Requires-Dist: jsonschema (>=4.25.0,<5.0.0)
Requires-Dist: packaging (>=25.0)
Requires-Dist: splunk-appinspect[validate] (>=4.0.0,<5.0.0) ; extra == "validate"
Project-URL: Bug Tracker, https://github.com/splunk/addonfactory-ucc-generator/issues
Project-URL: Documentation, https://splunk.github.io/addonfactory-ucc-generator
Project-URL: Homepage, https://github.com/splunk/addonfactory-ucc-generator
Project-URL: Repository, https://github.com/splunk/addonfactory-ucc-generator
